SimonControl.v
//==============================================================================
// Control Module for Simon Project
//==============================================================================

module SimonControl(
	// External Inputs
	input        clk,           // Clock
	input        rst,           // Reset

	// Datapath Inputs
    input         is_legal,
    input         correct_pattern,
    input         is_last_element,

	// Datapath Control Outputs
    output        reg scld, 
    output        reg rcld,
    output        reg rcclr,
    output        reg srld, 
    output        reg led_sel,

	// External Outputs
    output reg [2:0] mode_leds
);

	// Declare Local Vars Here
    reg [1:0] state;
    reg [1:0] next_state;

	// LED Light Parameters
    localparam LED_MODE_INPUT    = 3'b001;
    localparam LED_MODE_PLAYBACK = 3'b010;
    localparam LED_MODE_REPEAT   = 3'b100;
    localparam LED_MODE_DONE     = 3'b111;

	// Declare State Names Here
    localparam Input = 2'd0;
    localparam PlayBack = 2'd1;
    localparam Repeat = 2'd2;
    localparam Done = 2'd3;

	// Output Combinational Logic
	always @( * ) begin

        scld = 0; 
        rcld = 0; 
        rcclr = 0;
        srld = 0;
        led_sel = 0;

        case (state)
        // Write your output logic here
            Input: begin 
                if (is_legal) begin
                    srld = 1;
                    rcclr = 1;
                    scld = 1;
                end
                led_sel = 1;
                mode_leds = LED_MODE_INPUT;
            end

            PlayBack: begin 
                led_sel = 0;
                if (is_last_element) 
                    rcclr = 1;
                else 
                    rcld = 1;
                
                mode_leds = LED_MODE_PLAYBACK;
            end

            Repeat: begin 
                led_sel = 1;
                if (correct_pattern)
                    rcld = 1;
                else 
                    rcclr = 1;
                mode_leds = LED_MODE_REPEAT;
            end 

            Done: begin
                led_sel = 0;
                if (is_last_element)
                    rcclr = 1;
                else 
                    rcld = 1;
                mode_leds = LED_MODE_DONE;
            end

            default: begin 
                scld = 0; 
                rcld = 0; 
                rcclr = 0;
                srld = 0;
                led_sel = 0;
            end
        endcase
	end

	// Next State Combinational Logic
	always @( * ) begin
        
        next_state = Input; 
        case (state)

            Input: begin
                if (is_legal)
                    next_state = PlayBack;
                else 
                    next_state = state;
            end

            PlayBack: begin 
                if (is_last_element)
                    next_state = Repeat;
                else 
                    next_state = state;
            end 

            Repeat: begin
                if (correct_pattern && is_last_element)
                    next_state = Input;
                else if (~correct_pattern)
                    next_state = Done;
                else 
                    next_state = state;
            end

            Done: begin
                next_state = state;
            end

            default: begin
                next_state = Input;
            end
        endcase
	end

	// State Update Sequential Logic
	always @(posedge clk) begin
        if (rst) begin
            state <= Input;
        end
        else begin
            state <= next_state;
        end
	end

endmodule

SimonControl.t.v
//===============================================================================
// Testbench Module for Simon Controller
//===============================================================================
`timescale 1ns/100ps

`include "SimonControl.v"

// Print an error message (MSG) if value ONE is not equal
// to value TWO.
`define ASSERT_EQ(ONE, TWO, MSG)               \
	begin                                      \
		if ((ONE) !== (TWO)) begin             \
			$display("\t[FAILURE]:%s", (MSG)); \
			errors = errors + 1;               \
		end                                    \
	end #0

// Set the variable VAR to the value VALUE, printing a notification
// to the screen indicating the variable's update.
// The setting of the variable is preceeded and followed by
// a 1-timestep delay.
`define SET(VAR, VALUE) $display("Setting %s to %s...", "VAR", "VALUE"); #1; VAR = (VALUE); #1

// Cycle the clock up and then down, simulating
// a button press.
`define CLOCK $display("Pressing uclk..."); #1; clk = 1; #1; clk = 0; #1

module SimonControlTest;

	// External inputs
	reg clk = 0;
	reg rst = 0;

	// Datapath Inputs
    reg is_legal;
    reg correct_pattern;
    reg is_last_element;

	// Datapath Control Outputs
    wire scld;
    wire rcld;
    wire rcclr;
    wire srld;
    wire led_sel;

	// External Outputs
    wire [2:0] mode_leds;

	// Error Counts
	reg [7:0] errors = 0;

	// LED Light Parameters
	localparam LED_MODE_INPUT    = 3'b001;
	localparam LED_MODE_PLAYBACK = 3'b010;
	localparam LED_MODE_REPEAT   = 3'b100;
	localparam LED_MODE_DONE     = 3'b111;

	// VCD Dump
	initial begin
		$dumpfile("SimonControlTest.vcd");
		$dumpvars;
	end

	// Simon Control Module
	SimonControl ctrl(
		// External inputs
		.clk (clk),
		.rst (rst),

		// Datapath Inputs
		.is_legal (is_legal),
		.correct_pattern (correct_pattern),
		.is_last_element (is_last_element),

		// Datapath Control Outputs
		.scld (scld), 
		.rcld (rcld),
		.rcclr (rcclr),
		.srld (srld), 
		.led_sel (led_sel),

		// External Outputs
		.mode_leds (mode_leds)
	);

	// Main Test Logic
	initial begin
		// Case 1: Resetting the datapath to hard level
		// Input the values
		`SET(rst, 1);
		`SET(is_legal, 1);
		
		// Check the values
		`ASSERT_EQ(scld, 1'd0, "scld was not reset!");
		`ASSERT_EQ(rcld, 1'd0, "rcld were not reset!");
		`ASSERT_EQ(rcclr, 1'd0, "rcclr was not reset!");
        `ASSERT_EQ(srld, 1'd0, "srld was not reset!");
		`ASSERT_EQ(led_sel, 1'd0, "led_sel was not reset!");
		`ASSERT_EQ(mode_leds, 3'dx, "mode_leds were not reset!");

		// Case 2: Checking input mode
		// Input the values
		`CLOCK;
		`SET(rst, 0);
		`SET(is_legal, 1);
		`SET(correct_pattern, 0);
		`SET(is_last_element, 0);

		// Check the values
		`ASSERT_EQ(scld, 1'd1, "scld should be TRUE!");
		`ASSERT_EQ(rcld, 1'd0, "rcld should not have changed!");
		`ASSERT_EQ(rcclr, 1'd1, "rcclr should be TRUE!");
        `ASSERT_EQ(srld, 1'd1, "srld should be TRUE!");
		`ASSERT_EQ(led_sel, 1'd1, "led_sel should be TRUE!");
		`ASSERT_EQ(mode_leds, 3'b001, "mode_leds should be 001!");
		
		// Case 3: Checking playback mode
		// Input the values
		`CLOCK;
		`SET(is_legal, 1);
		`SET(correct_pattern, 1);
		`SET(is_last_element, 1);

		// Check the values
		`ASSERT_EQ(scld, 1'd0, "scld should be FALSE!");
		`ASSERT_EQ(rcld, 1'd0, "rcld should be FALSE!");
		`ASSERT_EQ(rcclr, 1'd1, "rcclr should be TRUE!");
        `ASSERT_EQ(srld, 1'd0, "srld should be FALSE!");
		`ASSERT_EQ(led_sel, 1'd0, "led_sel should be FALSE!");
		`ASSERT_EQ(mode_leds, 3'b010, "mode_leds should be 010!");

		// Case 4: Checking repeat mode
		// Input the values
		`CLOCK;
		`SET(is_legal, 1);
		`SET(correct_pattern, 0);
		`SET(is_last_element, 0);

		// Check the values
		`ASSERT_EQ(scld, 1'd0, "scld should be FALSE!");
		`ASSERT_EQ(rcld, 1'd0, "rcld should be FALSE!");
		`ASSERT_EQ(rcclr, 1'd1, "rcclr should be TRUE!");
        `ASSERT_EQ(srld, 1'd0, "srld should be FALSE!");
		`ASSERT_EQ(led_sel, 1'd1, "led_sel should be TRUE!");
		`ASSERT_EQ(mode_leds, 3'b100, "mode_leds should be 100!");

		// Case 5: Checking done mode
		// Input the values
		`CLOCK;
		`SET(is_legal, 1);
		`SET(correct_pattern, 0);
		`SET(is_last_element, 1);

		// Check the values
		`ASSERT_EQ(scld, 1'd0, "scld should be FALSE!");
		`ASSERT_EQ(rcld, 1'd0, "rcld should be FALSE!");
		`ASSERT_EQ(rcclr, 1'd1, "rcclr should be TRUE!");
        `ASSERT_EQ(srld, 1'd0, "srld should be FALSE!");
		`ASSERT_EQ(led_sel, 1'd0, "led_sel should be FALSE!");
		`ASSERT_EQ(mode_leds, 3'b111, "mode_leds should be 111!");

		// Case 6: Resetting the datapath to easy level
		// Input the values
		`CLOCK;
		`SET(rst, 1);
		`SET(is_legal, 0);

		// Check the values
		`ASSERT_EQ(scld, 1'd0, "scld should be FALSE!");
		`ASSERT_EQ(rcld, 1'd0, "rcld should be FALSE!");
		`ASSERT_EQ(rcclr, 1'd1, "rcclr should be TRUE!");
        `ASSERT_EQ(srld, 1'd0, "srld should be FALSE!");
		`ASSERT_EQ(led_sel, 1'd0, "led_sel should be FALSE!");
		`ASSERT_EQ(mode_leds, 3'b111, "mode_leds should be 111!");

		$display("\nTESTS COMPLETED (%d FAILURES)", errors);
		$finish;
	end

endmodule

SimonControlTest.vcd
$date
	Wed Nov 17 21:25:58 2021
$end
$version
	Icarus Verilog
$end
$timescale
	100ps
$end
$scope module SimonControlTest $end
$var wire 1 ! srld $end
$var wire 1 " scld $end
$var wire 1 # rcld $end
$var wire 1 $ rcclr $end
$var wire 3 % mode_leds [2:0] $end
$var wire 1 & led_sel $end
$var reg 1 ' clk $end
$var reg 1 ( correct_pattern $end
$var reg 8 ) errors [7:0] $end
$var reg 1 * is_last_element $end
$var reg 1 + is_legal $end
$var reg 1 , rst $end
$scope module ctrl $end
$var wire 1 ' clk $end
$var wire 1 ( correct_pattern $end
$var wire 1 * is_last_element $end
$var wire 1 + is_legal $end
$var wire 1 , rst $end
$var reg 1 & led_sel $end
$var reg 3 - mode_leds [2:0] $end
$var reg 2 . next_state [1:0] $end
$var reg 1 $ rcclr $end
$var reg 1 # rcld $end
$var reg 1 " scld $end
$var reg 1 ! srld $end
$var reg 2 / state [1:0] $end
$upscope $end
$upscope $end
$enddefinitions $end
#0
$dumpvars
bx /
bx .
bx -
0,
x+
x*
b0 )
x(
0'
x&
bx %
x$
x#
x"
x!
$end
#10
1,
#30
b0 .
0&
0!
0$
0#
0"
1+
#50
b1 %
b1 -
1&
1"
1$
1!
b1 .
b0 /
1'
#60
0'
#80
0,
#120
b1 .
1&
1!
1$
1"
0(
#140
1&
1!
1$
1"
b1 .
0*
#160
b1 .
b10 %
b10 -
1#
0&
0!
0$
0"
b1 /
1'
#170
0'
#210
1#
b1 .
1(
#230
b10 .
1$
0#
1*
#250
b100 %
b100 -
1#
1&
0$
b0 .
b10 /
1'
#260
0'
#300
b11 .
1$
1&
0#
0(
#320
1&
1$
b11 .
0*
#340
b11 .
b111 %
b111 -
1#
0&
0$
b11 /
1'
#350
0'
#410
1$
0#
b11 .
1*
#430
1'
#440
0'
#460
1,
#480
b11 .
1$
0+
